{
  "_8zUmHKob.js": {
    "resourceType": "script",
    "module": true,
    "prefetch": true,
    "preload": true,
    "file": "8zUmHKob.js",
    "name": "loadBackgroudImages"
  },
  "_BAo94QT0.js": {
    "resourceType": "script",
    "module": true,
    "prefetch": true,
    "preload": true,
    "file": "BAo94QT0.js",
    "name": "Footer1",
    "imports": [
      "_CQEHE1p5.js",
      "node_modules/nuxt/dist/app/entry.js"
    ]
  },
  "_BbrHkhRs.js": {
    "resourceType": "script",
    "module": true,
    "prefetch": true,
    "preload": true,
    "file": "BbrHkhRs.js",
    "name": "virtual_public",
    "imports": [
      "node_modules/nuxt/dist/app/entry.js"
    ]
  },
  "_BmZwJa2k.js": {
    "resourceType": "script",
    "module": true,
    "prefetch": true,
    "preload": true,
    "file": "BmZwJa2k.js",
    "name": "navigation",
    "imports": [
      "_D3Wqx-LM.js"
    ]
  },
  "_BmpBYS-P.js": {
    "resourceType": "script",
    "module": true,
    "prefetch": true,
    "preload": true,
    "file": "BmpBYS-P.js",
    "name": "nuxt-link",
    "imports": [
      "node_modules/nuxt/dist/app/entry.js"
    ]
  },
  "_C2SlALem.js": {
    "resourceType": "script",
    "module": true,
    "prefetch": true,
    "preload": true,
    "file": "C2SlALem.js",
    "name": "pagination",
    "imports": [
      "_D3Wqx-LM.js",
      "_BmZwJa2k.js"
    ]
  },
  "_C94R5R1w.js": {
    "resourceType": "script",
    "module": true,
    "prefetch": true,
    "preload": true,
    "file": "C94R5R1w.js",
    "name": "removeSlashFromPagination",
    "imports": [
      "node_modules/nuxt/dist/app/entry.js"
    ]
  },
  "_CQEHE1p5.js": {
    "resourceType": "script",
    "module": true,
    "prefetch": true,
    "preload": true,
    "file": "CQEHE1p5.js",
    "name": "virtual_public",
    "imports": [
      "node_modules/nuxt/dist/app/entry.js"
    ]
  },
  "_CUSYfIpl.js": {
    "resourceType": "script",
    "module": true,
    "prefetch": true,
    "preload": true,
    "file": "CUSYfIpl.js",
    "name": "autoplay",
    "imports": [
      "_D3Wqx-LM.js"
    ]
  },
  "_CWz3FyRx.js": {
    "resourceType": "script",
    "module": true,
    "prefetch": true,
    "preload": true,
    "file": "CWz3FyRx.js",
    "name": "Header",
    "imports": [
      "node_modules/nuxt/dist/app/entry.js"
    ]
  },
  "_CXzKLdEG.js": {
    "resourceType": "script",
    "module": true,
    "prefetch": true,
    "preload": true,
    "file": "CXzKLdEG.js",
    "name": "Menu",
    "imports": [
      "_BmpBYS-P.js",
      "_CQEHE1p5.js",
      "node_modules/nuxt/dist/app/entry.js"
    ]
  },
  "_C_Za6c8D.js": {
    "resourceType": "script",
    "module": true,
    "prefetch": true,
    "preload": true,
    "file": "C_Za6c8D.js",
    "name": "initIsotope"
  },
  "_Cbf3TdT0.js": {
    "resourceType": "script",
    "module": true,
    "prefetch": true,
    "preload": true,
    "file": "Cbf3TdT0.js",
    "name": "hoverEffect1"
  },
  "_CxwB9NdW.js": {
    "resourceType": "script",
    "module": true,
    "prefetch": true,
    "preload": true,
    "file": "CxwB9NdW.js",
    "name": "keyboard",
    "imports": [
      "_D3Wqx-LM.js"
    ]
  },
  "_D3Wqx-LM.js": {
    "resourceType": "script",
    "module": true,
    "prefetch": true,
    "preload": true,
    "file": "D3Wqx-LM.js",
    "name": "swiper-slide",
    "imports": [
      "node_modules/nuxt/dist/app/entry.js"
    ]
  },
  "_Dbxlwa6B.js": {
    "resourceType": "script",
    "module": true,
    "prefetch": true,
    "preload": true,
    "file": "Dbxlwa6B.js",
    "name": "ProgressScroll",
    "imports": [
      "node_modules/nuxt/dist/app/entry.js"
    ]
  },
  "_GO9ooWng.js": {
    "resourceType": "script",
    "module": true,
    "prefetch": true,
    "preload": true,
    "file": "GO9ooWng.js",
    "name": "virtual_public",
    "imports": [
      "node_modules/nuxt/dist/app/entry.js"
    ]
  },
  "_SAYOHZ9n.js": {
    "resourceType": "script",
    "module": true,
    "prefetch": true,
    "preload": true,
    "file": "SAYOHZ9n.js",
    "name": "mousewheel",
    "imports": [
      "_D3Wqx-LM.js"
    ]
  },
  "_UC-kMiIZ.js": {
    "resourceType": "script",
    "module": true,
    "prefetch": true,
    "preload": true,
    "file": "UC-kMiIZ.js",
    "name": "vue.f36acd1f",
    "imports": [
      "node_modules/nuxt/dist/app/entry.js"
    ]
  },
  "layouts/default.vue": {
    "resourceType": "script",
    "module": true,
    "prefetch": true,
    "preload": true,
    "file": "DgaiD_Tt.js",
    "name": "default",
    "src": "layouts/default.vue",
    "isDynamicEntry": true,
    "imports": [
      "_Dbxlwa6B.js",
      "node_modules/nuxt/dist/app/entry.js"
    ]
  },
  "layouts/preview.vue": {
    "resourceType": "script",
    "module": true,
    "prefetch": true,
    "preload": true,
    "file": "zU4DiPlM.js",
    "name": "preview",
    "src": "layouts/preview.vue",
    "isDynamicEntry": true,
    "imports": [
      "_Dbxlwa6B.js",
      "_UC-kMiIZ.js",
      "node_modules/nuxt/dist/app/entry.js"
    ]
  },
  "node_modules/@nuxt/ui-templates/dist/templates/error-404.vue": {
    "resourceType": "script",
    "module": true,
    "prefetch": true,
    "preload": true,
    "file": "BQLOg3rz.js",
    "name": "error-404",
    "src": "node_modules/@nuxt/ui-templates/dist/templates/error-404.vue",
    "isDynamicEntry": true,
    "imports": [
      "_BmpBYS-P.js",
      "_UC-kMiIZ.js",
      "node_modules/nuxt/dist/app/entry.js"
    ],
    "css": []
  },
  "error-404.JekaaCis.css": {
    "file": "error-404.JekaaCis.css",
    "resourceType": "style",
    "prefetch": true,
    "preload": true
  },
  "node_modules/@nuxt/ui-templates/dist/templates/error-500.vue": {
    "resourceType": "script",
    "module": true,
    "prefetch": true,
    "preload": true,
    "file": "CenuKwMR.js",
    "name": "error-500",
    "src": "node_modules/@nuxt/ui-templates/dist/templates/error-500.vue",
    "isDynamicEntry": true,
    "imports": [
      "_UC-kMiIZ.js",
      "node_modules/nuxt/dist/app/entry.js"
    ],
    "css": []
  },
  "error-500.CNP9nqm1.css": {
    "file": "error-500.CNP9nqm1.css",
    "resourceType": "style",
    "prefetch": true,
    "preload": true
  },
  "node_modules/nuxt/dist/app/entry.js": {
    "resourceType": "script",
    "module": true,
    "prefetch": true,
    "preload": true,
    "file": "BKIlW9GU.js",
    "name": "entry",
    "src": "node_modules/nuxt/dist/app/entry.js",
    "isEntry": true,
    "dynamicImports": [
      "layouts/default.vue",
      "layouts/preview.vue",
      "node_modules/@nuxt/ui-templates/dist/templates/error-404.vue",
      "node_modules/@nuxt/ui-templates/dist/templates/error-500.vue"
    ],
    "_globalCSS": true
  },
  "pages/about.vue": {
    "resourceType": "script",
    "module": true,
    "prefetch": true,
    "preload": true,
    "file": "Di81GIaF.js",
    "name": "about",
    "src": "pages/about.vue",
    "isDynamicEntry": true,
    "imports": [
      "_CQEHE1p5.js",
      "_CXzKLdEG.js",
      "node_modules/nuxt/dist/app/entry.js",
      "_GO9ooWng.js",
      "_C94R5R1w.js",
      "_D3Wqx-LM.js",
      "_BmZwJa2k.js",
      "_C2SlALem.js",
      "_BAo94QT0.js",
      "_UC-kMiIZ.js",
      "_BmpBYS-P.js"
    ]
  },
  "pages/blog-details.vue": {
    "resourceType": "script",
    "module": true,
    "prefetch": true,
    "preload": true,
    "file": "BGqRYADf.js",
    "name": "blog-details",
    "src": "pages/blog-details.vue",
    "isDynamicEntry": true,
    "imports": [
      "_CQEHE1p5.js",
      "_CXzKLdEG.js",
      "node_modules/nuxt/dist/app/entry.js",
      "_8zUmHKob.js",
      "_BAo94QT0.js",
      "_UC-kMiIZ.js",
      "_BmpBYS-P.js"
    ]
  },
  "pages/blog.vue": {
    "resourceType": "script",
    "module": true,
    "prefetch": true,
    "preload": true,
    "file": "C09jVFd1.js",
    "name": "blog",
    "src": "pages/blog.vue",
    "isDynamicEntry": true,
    "imports": [
      "_CQEHE1p5.js",
      "_CXzKLdEG.js",
      "node_modules/nuxt/dist/app/entry.js",
      "_C_Za6c8D.js",
      "_BAo94QT0.js",
      "_UC-kMiIZ.js",
      "_BmpBYS-P.js"
    ]
  },
  "pages/carousel-slider.vue": {
    "resourceType": "script",
    "module": true,
    "prefetch": true,
    "preload": true,
    "file": "BYdXZARQ.js",
    "name": "carousel-slider",
    "src": "pages/carousel-slider.vue",
    "isDynamicEntry": true,
    "imports": [
      "_CQEHE1p5.js",
      "_CXzKLdEG.js",
      "_D3Wqx-LM.js",
      "_CxwB9NdW.js",
      "_SAYOHZ9n.js",
      "_BmZwJa2k.js",
      "_C2SlALem.js",
      "_CUSYfIpl.js",
      "_8zUmHKob.js",
      "node_modules/nuxt/dist/app/entry.js",
      "_UC-kMiIZ.js",
      "_BmpBYS-P.js"
    ]
  },
  "pages/contact.vue": {
    "resourceType": "script",
    "module": true,
    "prefetch": true,
    "preload": true,
    "file": "C4CQuX0i.js",
    "name": "contact",
    "src": "pages/contact.vue",
    "isDynamicEntry": true,
    "imports": [
      "_CQEHE1p5.js",
      "_CXzKLdEG.js",
      "node_modules/nuxt/dist/app/entry.js",
      "_BAo94QT0.js",
      "_UC-kMiIZ.js",
      "_BmpBYS-P.js"
    ]
  },
  "pages/creative-agency.vue": {
    "resourceType": "script",
    "module": true,
    "prefetch": true,
    "preload": true,
    "file": "CEitry5A.js",
    "name": "creative-agency",
    "src": "pages/creative-agency.vue",
    "isDynamicEntry": true,
    "imports": [
      "_CQEHE1p5.js",
      "_CXzKLdEG.js",
      "node_modules/nuxt/dist/app/entry.js",
      "_C94R5R1w.js",
      "_D3Wqx-LM.js",
      "_BmZwJa2k.js",
      "_C2SlALem.js",
      "_BAo94QT0.js",
      "_UC-kMiIZ.js",
      "_BmpBYS-P.js"
    ]
  },
  "pages/creative-portfolio.vue": {
    "resourceType": "script",
    "module": true,
    "prefetch": true,
    "preload": true,
    "file": "ARQ8KYOK.js",
    "name": "creative-portfolio",
    "src": "pages/creative-portfolio.vue",
    "isDynamicEntry": true,
    "imports": [
      "_CQEHE1p5.js",
      "_CXzKLdEG.js",
      "node_modules/nuxt/dist/app/entry.js",
      "_BmpBYS-P.js",
      "_D3Wqx-LM.js",
      "_BmZwJa2k.js",
      "_C94R5R1w.js",
      "_C2SlALem.js",
      "_BAo94QT0.js",
      "_UC-kMiIZ.js"
    ]
  },
  "pages/fullscreen.vue": {
    "resourceType": "script",
    "module": true,
    "prefetch": true,
    "preload": true,
    "file": "BWatwflj.js",
    "name": "fullscreen",
    "src": "pages/fullscreen.vue",
    "isDynamicEntry": true,
    "imports": [
      "_CQEHE1p5.js",
      "_CXzKLdEG.js",
      "_D3Wqx-LM.js",
      "_SAYOHZ9n.js",
      "_BmZwJa2k.js",
      "_C2SlALem.js",
      "_CUSYfIpl.js",
      "_8zUmHKob.js",
      "node_modules/nuxt/dist/app/entry.js",
      "_UC-kMiIZ.js",
      "_BmpBYS-P.js"
    ]
  },
  "pages/half-slider.vue": {
    "resourceType": "script",
    "module": true,
    "prefetch": true,
    "preload": true,
    "file": "DuhBQUPL.js",
    "name": "half-slider",
    "src": "pages/half-slider.vue",
    "isDynamicEntry": true,
    "imports": [
      "_CQEHE1p5.js",
      "_CXzKLdEG.js",
      "_D3Wqx-LM.js",
      "_CxwB9NdW.js",
      "_SAYOHZ9n.js",
      "_BmZwJa2k.js",
      "_C2SlALem.js",
      "_8zUmHKob.js",
      "node_modules/nuxt/dist/app/entry.js",
      "_UC-kMiIZ.js",
      "_BmpBYS-P.js"
    ]
  },
  "pages/index.vue": {
    "resourceType": "script",
    "module": true,
    "prefetch": true,
    "preload": true,
    "file": "N6HGOmpK.js",
    "name": "index",
    "src": "pages/index.vue",
    "isDynamicEntry": true,
    "imports": [
      "_CQEHE1p5.js",
      "node_modules/nuxt/dist/app/entry.js",
      "_UC-kMiIZ.js"
    ]
  },
  "pages/interactive-center.vue": {
    "resourceType": "script",
    "module": true,
    "prefetch": true,
    "preload": true,
    "file": "BWAIzdqK.js",
    "name": "interactive-center",
    "src": "pages/interactive-center.vue",
    "isDynamicEntry": true,
    "imports": [
      "_CQEHE1p5.js",
      "_CXzKLdEG.js",
      "_Cbf3TdT0.js",
      "node_modules/nuxt/dist/app/entry.js",
      "_UC-kMiIZ.js",
      "_BmpBYS-P.js"
    ]
  },
  "pages/interactive-full.vue": {
    "resourceType": "script",
    "module": true,
    "prefetch": true,
    "preload": true,
    "file": "Dm0Zx_yu.js",
    "name": "interactive-full",
    "src": "pages/interactive-full.vue",
    "isDynamicEntry": true,
    "imports": [
      "_CQEHE1p5.js",
      "_CXzKLdEG.js",
      "node_modules/nuxt/dist/app/entry.js",
      "_UC-kMiIZ.js",
      "_BmpBYS-P.js"
    ]
  },
  "pages/interactive-inline.vue": {
    "resourceType": "script",
    "module": true,
    "prefetch": true,
    "preload": true,
    "file": "CGsB5sAZ.js",
    "name": "interactive-inline",
    "src": "pages/interactive-inline.vue",
    "isDynamicEntry": true,
    "imports": [
      "_CQEHE1p5.js",
      "_CXzKLdEG.js",
      "_Cbf3TdT0.js",
      "node_modules/nuxt/dist/app/entry.js",
      "_UC-kMiIZ.js",
      "_BmpBYS-P.js"
    ]
  },
  "pages/interactive-vertical.vue": {
    "resourceType": "script",
    "module": true,
    "prefetch": true,
    "preload": true,
    "file": "D3l-fRrH.js",
    "name": "interactive-vertical",
    "src": "pages/interactive-vertical.vue",
    "isDynamicEntry": true,
    "imports": [
      "_CQEHE1p5.js",
      "_CXzKLdEG.js",
      "node_modules/nuxt/dist/app/entry.js",
      "_UC-kMiIZ.js",
      "_BmpBYS-P.js"
    ]
  },
  "pages/landing.vue": {
    "resourceType": "script",
    "module": true,
    "prefetch": true,
    "preload": true,
    "file": "DBwfgS_2.js",
    "name": "landing",
    "src": "pages/landing.vue",
    "isDynamicEntry": true,
    "imports": [
      "_CQEHE1p5.js",
      "_CXzKLdEG.js",
      "node_modules/nuxt/dist/app/entry.js",
      "_GO9ooWng.js",
      "_D3Wqx-LM.js",
      "_BAo94QT0.js",
      "_UC-kMiIZ.js",
      "_BmpBYS-P.js"
    ]
  },
  "pages/portfolio-fixed-text.vue": {
    "resourceType": "script",
    "module": true,
    "prefetch": true,
    "preload": true,
    "file": "CEC0H0jt.js",
    "name": "portfolio-fixed-text",
    "src": "pages/portfolio-fixed-text.vue",
    "isDynamicEntry": true,
    "imports": [
      "_CQEHE1p5.js",
      "_CXzKLdEG.js",
      "_CWz3FyRx.js",
      "node_modules/nuxt/dist/app/entry.js",
      "_BAo94QT0.js",
      "_UC-kMiIZ.js",
      "_BmpBYS-P.js"
    ]
  },
  "pages/portfolio-grid-classic.vue": {
    "resourceType": "script",
    "module": true,
    "prefetch": true,
    "preload": true,
    "file": "BVWyTkSY.js",
    "name": "portfolio-grid-classic",
    "src": "pages/portfolio-grid-classic.vue",
    "isDynamicEntry": true,
    "imports": [
      "_CQEHE1p5.js",
      "_CXzKLdEG.js",
      "_CWz3FyRx.js",
      "_C_Za6c8D.js",
      "node_modules/nuxt/dist/app/entry.js",
      "_BAo94QT0.js",
      "_UC-kMiIZ.js",
      "_BmpBYS-P.js"
    ]
  },
  "pages/portfolio-grid.vue": {
    "resourceType": "script",
    "module": true,
    "prefetch": true,
    "preload": true,
    "file": "XqFJrnH7.js",
    "name": "portfolio-grid",
    "src": "pages/portfolio-grid.vue",
    "isDynamicEntry": true,
    "imports": [
      "_CQEHE1p5.js",
      "_CXzKLdEG.js",
      "_CWz3FyRx.js",
      "_C_Za6c8D.js",
      "node_modules/nuxt/dist/app/entry.js",
      "_BAo94QT0.js",
      "_UC-kMiIZ.js",
      "_BmpBYS-P.js"
    ]
  },
  "pages/project1.vue": {
    "resourceType": "script",
    "module": true,
    "prefetch": true,
    "preload": true,
    "file": "BN-3yaCi.js",
    "name": "project1",
    "src": "pages/project1.vue",
    "isDynamicEntry": true,
    "imports": [
      "_CQEHE1p5.js",
      "_CXzKLdEG.js",
      "_8zUmHKob.js",
      "node_modules/nuxt/dist/app/entry.js",
      "_BbrHkhRs.js",
      "_BAo94QT0.js",
      "_UC-kMiIZ.js",
      "_BmpBYS-P.js"
    ]
  },
  "pages/project2.vue": {
    "resourceType": "script",
    "module": true,
    "prefetch": true,
    "preload": true,
    "file": "CcZfiFM3.js",
    "name": "project2",
    "src": "pages/project2.vue",
    "isDynamicEntry": true,
    "imports": [
      "_CQEHE1p5.js",
      "_CXzKLdEG.js",
      "node_modules/nuxt/dist/app/entry.js",
      "_D3Wqx-LM.js",
      "_BmZwJa2k.js",
      "_CUSYfIpl.js",
      "_BbrHkhRs.js",
      "_BAo94QT0.js",
      "_UC-kMiIZ.js",
      "_BmpBYS-P.js"
    ]
  },
  "pages/project3.vue": {
    "resourceType": "script",
    "module": true,
    "prefetch": true,
    "preload": true,
    "file": "DNhZGvvC.js",
    "name": "project3",
    "src": "pages/project3.vue",
    "isDynamicEntry": true,
    "imports": [
      "_CQEHE1p5.js",
      "_CXzKLdEG.js",
      "_8zUmHKob.js",
      "node_modules/nuxt/dist/app/entry.js",
      "_BbrHkhRs.js",
      "_BAo94QT0.js",
      "_UC-kMiIZ.js",
      "_BmpBYS-P.js"
    ]
  },
  "pages/project4.vue": {
    "resourceType": "script",
    "module": true,
    "prefetch": true,
    "preload": true,
    "file": "DZIxgWNm.js",
    "name": "project4",
    "src": "pages/project4.vue",
    "isDynamicEntry": true,
    "imports": [
      "_CQEHE1p5.js",
      "_CXzKLdEG.js",
      "_8zUmHKob.js",
      "node_modules/nuxt/dist/app/entry.js",
      "_BbrHkhRs.js",
      "_BAo94QT0.js",
      "_UC-kMiIZ.js",
      "_BmpBYS-P.js"
    ]
  }
}